thumbor_spaces/__init__.py
thumbor_spaces/loaders/__init__.py
thumbor_spaces/loaders/spaces_loader.py
thumbor_spaces/result_storages/__init__.py
thumbor_spaces/result_storages/spaces_storage.py
thumbor_spaces-2.21.dist-info/LICENSE
thumbor_spaces-2.21.dist-info/METADATA
thumbor_spaces-2.21.dist-info/WHEEL
thumbor_spaces-2.21.dist-info/top_level.txt
thumbor_spaces-2.21.dist-info/RECORD
