Metadata-Version: 2.1
Name: thumbor-spaces
Version: 2.21
Summary: spaces addons for Thumbor
Home-page: https://github.com/siddhartham/thumbor_spaces
Author: Siddhartha Mukherjee
Author-email: mukherjee.siddhartha@gmail.com
License: MIT
Keywords: thumbor,spaces,images,cloud
Platform: UNKNOWN
Classifier: Development Status :: 3 - Alpha
Classifier: Intended Audience :: Developers
Classifier: License :: OSI Approved :: MIT License
Classifier: Natural Language :: English
Classifier: Operating System :: POSIX :: Linux
Classifier: Programming Language :: Python :: 2.7
Classifier: Topic :: Internet :: WWW/HTTP :: Dynamic Content
Classifier: Topic :: Multimedia :: Graphics :: Presentation
Requires: thumbor
